{
  "moduleId": "plantCareTracker",
  "moduleName": "PlantCareTracker",
  "displayName": "Plant Care Tracker",
  "shortName": "Plants",
  "subtitle": "Keep your green friends thriving",
  "icon": "leaf.fill",
  "iconColor": "hubAccentGreen",
  "relevanceKeywords": [
    "plant",
    "watering",
    "garden",
    "houseplant",
    "fertilize",
    "greenery",
    "botanical",
    "succulent",
    "herb",
    "care"
  ],
  "dataFields": [
    {
      "name": "plantName",
      "type": "String",
      "label": "Plant Name",
      "control": "text"
    },
    {
      "name": "careType",
      "type": "CareType",
      "label": "Care Type",
      "control": "picker"
    },
    {
      "name": "waterAmount",
      "type": "WaterAmount",
      "label": "Water Amount",
      "control": "picker"
    },
    {
      "name": "healthRating",
      "type": "Int",
      "label": "Health Rating (1-5)",
      "control": "slider"
    },
    {
      "name": "location",
      "type": "PlantLocation",
      "label": "Location",
      "control": "picker"
    },
    {
      "name": "usedFertilizer",
      "type": "Bool",
      "label": "Added Fertilizer",
      "control": "toggle"
    },
    {
      "name": "notes",
      "type": "String",
      "label": "Observations",
      "control": "text"
    }
  ],
  "enums": [
    {
      "name": "CareType",
      "cases": [
        {
          "name": "watering",
          "displayName": "Watering",
          "icon": "drop.fill"
        },
        {
          "name": "misting",
          "displayName": "Misting",
          "icon": "humidity.fill"
        },
        {
          "name": "fertilizing",
          "displayName": "Fertilizing",
          "icon": "leaf.arrow.circlepath"
        },
        {
          "name": "pruning",
          "displayName": "Pruning",
          "icon": "scissors"
        },
        {
          "name": "repotting",
          "displayName": "Repotting",
          "icon": "arrow.up.bin.fill"
        }
      ]
    },
    {
      "name": "WaterAmount",
      "cases": [
        {
          "name": "light",
          "displayName": "Light Splash",
          "icon": "drop"
        },
        {
          "name": "moderate",
          "displayName": "Moderate",
          "icon": "drop.halffull"
        },
        {
          "name": "thorough",
          "displayName": "Thorough",
          "icon": "drop.fill"
        },
        {
          "name": "soaking",
          "displayName": "Deep Soak",
          "icon": "water.waves"
        }
      ]
    },
    {
      "name": "PlantLocation",
      "cases": [
        {
          "name": "livingRoom",
          "displayName": "Living Room",
          "icon": "sofa.fill"
        },
        {
          "name": "bedroom",
          "displayName": "Bedroom",
          "icon": "bed.double.fill"
        },
        {
          "name": "kitchen",
          "displayName": "Kitchen",
          "icon": "fork.knife"
        },
        {
          "name": "bathroom",
          "displayName": "Bathroom",
          "icon": "shower.fill"
        },
        {
          "name": "office",
          "displayName": "Office",
          "icon": "desktopcomputer"
        },
        {
          "name": "balcony",
          "displayName": "Balcony",
          "icon": "sun.max.fill"
        },
        {
          "name": "garden",
          "displayName": "Garden",
          "icon": "tree.fill"
        },
        {
          "name": "other",
          "displayName": "Other",
          "icon": "mappin"
        }
      ]
    }
  ],
  "views": [
    {
      "name": "DashboardView",
      "purpose": "Main dashboard showing today's watering summary, plants needing attention, health overview ring, and quick-add button",
      "components": [
        "StatGrid",
        "ProgressRingView",
        "NeglectedPlantsAlert",
        "QuickEntryFAB"
      ]
    },
    {
      "name": "EntrySheet",
      "purpose": "Quick entry modal to log a watering or care event for a specific plant with smart defaults based on recent history",
      "components": [
        "PlantNameAutocomplete",
        "CareTypePicker",
        "WaterAmountSelector",
        "HealthSlider",
        "LocationPicker"
      ]
    },
    {
      "name": "HistoryView",
      "purpose": "Date-grouped care log filterable by plant name, care type, and location with color-coded care type badges",
      "components": [
        "CalendarHeatmap",
        "FilterableEntryList",
        "PlantGroupedView"
      ]
    },
    {
      "name": "AnalyticsView",
      "purpose": "Charts showing watering frequency trends, health ratings over time per plant, care type distribution, and location breakdown with actionable insights",
      "components": [
        "ModuleChartView",
        "HealthTrendChart",
        "CareDistributionPie",
        "InsightsList"
      ]
    }
  ],
  "viewModelComputedProperties": [
    {
      "name": "todayWateringCount",
      "type": "Int",
      "description": "Number of plants watered today across all care types"
    },
    {
      "name": "plantsWateredToday",
      "type": "[String]",
      "description": "Unique plant names that received care today"
    },
    {
      "name": "weeklyWateringCount",
      "type": "Int",
      "description": "Total care events logged in the current week (Mon-Sun)"
    },
    {
      "name": "currentStreak",
      "type": "Int",
      "description": "Consecutive days with at least one watering event logged"
    },
    {
      "name": "uniquePlantCount",
      "type": "Int",
      "description": "Total number of unique plants being tracked across all entries"
    },
    {
      "name": "neglectedPlants",
      "type": "[String]",
      "description": "Plant names whose last watering was more than 7 days ago, sorted by urgency"
    },
    {
      "name": "averageHealthRating",
      "type": "Double",
      "description": "Mean health rating across the most recent entry for each unique plant"
    },
    {
      "name": "healthTrend",
      "type": "String",
      "description": "Compares average health rating this week vs last week: improving, declining, or stable"
    },
    {
      "name": "mostCaredPlant",
      "type": "String",
      "description": "Plant name with the highest number of care entries in the last 30 days"
    },
    {
      "name": "careTypeBreakdown",
      "type": "[(String, Int)]",
      "description": "Distribution of care types (watering, misting, etc.) as label-count pairs for pie chart"
    },
    {
      "name": "weeklyChartData",
      "type": "[(Date, Int)]",
      "description": "Daily watering counts for the past 7 days as date-value pairs for bar chart"
    },
    {
      "name": "goalProgress",
      "type": "Double",
      "description": "Fraction of daily watering goal completed (todayWateringCount / dailyGoal), clamped 0-1"
    },
    {
      "name": "plantHealthMap",
      "type": "[(String, Int)]",
      "description": "Each unique plant paired with its most recent health rating for health overview grid"
    },
    {
      "name": "insights",
      "type": "[String]",
      "description": "Generated insight strings: neglected plant alerts, streak celebrations, health warnings, fertilizer reminders"
    }
  ],
  "domainLogic": {
    "dailyGoal": {
      "description": "Target number of plants to check and water per day, encourages consistent daily plant rounds",
      "defaultValue": "3"
    },
    "streakDefinition": "A day counts as active if at least one watering-type care event (watering or misting) is logged. Fertilizing, pruning, and repotting do not count toward the streak since they are infrequent tasks.",
    "trendAnalysis": "Track weekly average watering count vs previous week (volume trend), average health rating this week vs last week (health trend), and per-plant watering frequency to detect neglected plants (any plant with no watering entry in 7+ days triggers an alert).",
    "insights": [
      "Neglected plant alert: '{plantName} hasn't been watered in {days} days' when last watering exceeds 7 days",
      "Streak celebration: 'Amazing! {streak}-day green thumb streak!' at 7, 14, 30, 60, 90 day milestones",
      "Health warning: '{plantName} health declining \u2014 rated {rating}/5, down from {previous}' when latest health rating drops 2+ points from 30-day average",
      "Fertilizer reminder: 'Consider fertilizing {plantName} \u2014 last fertilized {days} days ago' when no fertilize entry in 30+ days",
      "Consistency insight: 'You watered {percent}% more plants this week vs last week' comparing weekly totals",
      "Top performer: '{plantName} is thriving at {rating}/5 health!' for plant with highest recent health rating"
    ]
  }
}