{
  "moduleId": "habitTracker",
  "moduleName": "HabitTracker",
  "displayName": "Habit Tracker",
  "shortName": "Habits",
  "subtitle": "Build streaks, build yourself",
  "icon": "checkmark.circle.fill",
  "iconColor": "hubAccentGreen",
  "relevanceKeywords": [
    "habit",
    "streak",
    "routine",
    "daily",
    "meditation",
    "journaling",
    "consistency",
    "ritual",
    "discipline",
    "check"
  ],
  "navigationPattern": "tabbedSegmented",
  "entryPattern": "sheet",
  "dataFields": [
    {
      "name": "name",
      "type": "String",
      "label": "Habit Name",
      "control": "text"
    },
    {
      "name": "habitIcon",
      "type": "String",
      "label": "Icon",
      "control": "text"
    },
    {
      "name": "category",
      "type": "HabitCategory",
      "label": "Category",
      "control": "picker"
    },
    {
      "name": "timeOfDay",
      "type": "TimeOfDay",
      "label": "Time of Day",
      "control": "picker"
    },
    {
      "name": "targetDaysPerWeek",
      "type": "Int",
      "label": "Days per Week",
      "control": "stepper"
    },
    {
      "name": "isArchived",
      "type": "Bool",
      "label": "Archived",
      "control": "toggle"
    }
  ],
  "enums": [
    {
      "name": "HabitCategory",
      "cases": [
        {
          "name": "health",
          "displayName": "Health",
          "icon": "heart.fill"
        },
        {
          "name": "mindfulness",
          "displayName": "Mindfulness",
          "icon": "brain.head.profile"
        },
        {
          "name": "productivity",
          "displayName": "Productivity",
          "icon": "bolt.fill"
        },
        {
          "name": "fitness",
          "displayName": "Fitness",
          "icon": "figure.run"
        },
        {
          "name": "learning",
          "displayName": "Learning",
          "icon": "book.fill"
        },
        {
          "name": "selfCare",
          "displayName": "Self Care",
          "icon": "sparkles"
        },
        {
          "name": "social",
          "displayName": "Social",
          "icon": "person.2.fill"
        },
        {
          "name": "other",
          "displayName": "Other",
          "icon": "square.grid.2x2.fill"
        }
      ]
    },
    {
      "name": "TimeOfDay",
      "cases": [
        {
          "name": "morning",
          "displayName": "Morning",
          "icon": "sunrise.fill"
        },
        {
          "name": "afternoon",
          "displayName": "Afternoon",
          "icon": "sun.max.fill"
        },
        {
          "name": "evening",
          "displayName": "Evening",
          "icon": "sunset.fill"
        },
        {
          "name": "anytime",
          "displayName": "Anytime",
          "icon": "clock.fill"
        }
      ]
    }
  ],
  "views": [
    {
      "name": "TodayView",
      "purpose": "Primary interaction screen. Top area shows a large circular progress ring with today's completion fraction (e.g. 5/8) and a motivational label. Below, habits are grouped into collapsible sections by timeOfDay (Morning, Afternoon, Evening, Anytime). Each habit row shows: its SF Symbol icon in a tinted circle, the habit name, a small flame icon with current streak count, and a circular tap-to-complete button on the right. Tapping the button marks the habit done with a scale-up animation and haptic feedback; the row gets a subtle green-tinted background. Completed habits sort to the bottom of their section. The progress ring animates as habits are checked off.",
      "components": [
        "ProgressRing",
        "HabitRow",
        "StreakBadge",
        "TimeOfDaySection"
      ],
      "isTab": true,
      "tabLabel": "Today",
      "tabIcon": "checkmark.circle"
    },
    {
      "name": "StreaksView",
      "purpose": "Visual streak showcase. Top section is a GitHub-style 12-week contribution heatmap calendar \u2014 each cell represents one day, colored from gray (0%) through light green to dark green (100% habits completed). Tapping a day shows a popover listing which habits were completed. Below the heatmap, a vertically scrolling list of per-habit streak cards sorted by current streak descending. Each card shows: habit icon, name, current streak with flame emoji and day count, best-ever streak with trophy icon, and a 7-day trailing dot strip (filled green dot = completed, hollow gray dot = missed). Cards for habits with streaks above 7 days get a subtle golden border glow.",
      "components": [
        "CalendarHeatmap",
        "StreakCard",
        "WeekDotStrip",
        "DayPopover"
      ],
      "isTab": true,
      "tabLabel": "Streaks",
      "tabIcon": "flame"
    },
    {
      "name": "StatsView",
      "purpose": "Analytics and insights. Top card shows this week's average daily completion rate as a large percentage with a trend arrow comparing to last week (green up arrow or red down arrow). Second section is a horizontal bar chart of completion rates by HabitCategory \u2014 each bar is tinted with the category's icon color, label on left, percentage on right. Third section shows best day of the week as a row of 7 day-circles (M T W T F S S) with fill proportional to 4-week rolling average completion rate. Bottom section shows earned milestone badges in a flowing grid \u2014 badges for 7-day, 30-day, 60-day, and 100-day streaks with the habit name, using bronze/silver/gold/platinum tinting respectively. Recently earned milestones pulse with a subtle glow animation.",
      "components": [
        "TrendCard",
        "CategoryBarChart",
        "DayOfWeekCircles",
        "MilestoneBadge"
      ],
      "isTab": true,
      "tabLabel": "Stats",
      "tabIcon": "chart.bar"
    },
    {
      "name": "HabitEntrySheet",
      "purpose": "Modal sheet for creating or editing a habit definition. Sections: (1) Name text field with placeholder 'e.g. Meditate 10 min'. (2) Icon picker \u2014 a scrollable grid of 24 curated SF Symbols commonly used for habits (figure.mind.and.body, book.fill, drop.fill, dumbbell.fill, pencil.and.outline, bed.double.fill, etc.) with the selected one highlighted in hubPrimary. (3) Category picker using a horizontal scrolling row of labeled icons. (4) Time of Day segmented picker. (5) Target days per week stepper (1\u20137) with label showing 'Daily' for 7 or 'X days/week' otherwise. Save button at bottom, disabled until name is non-empty.",
      "components": [
        "IconPickerGrid",
        "CategoryScrollRow",
        "DaysPerWeekStepper"
      ],
      "isTab": false,
      "tabLabel": "",
      "tabIcon": ""
    }
  ],
  "viewModelComputedProperties": [
    {
      "name": "activeHabits",
      "type": "[HabitTrackerEntry]",
      "description": "All habits where isArchived is false, sorted by timeOfDay ordinal then name alphabetically"
    },
    {
      "name": "habitsByTimeOfDay",
      "type": "[TimeOfDay: [HabitTrackerEntry]]",
      "description": "Active habits grouped by their timeOfDay value for sectioned Today view display"
    },
    {
      "name": "todayCompletions",
      "type": "Set<String>",
      "description": "Set of habit IDs that have been marked complete for today, persisted in UserDefaults keyed by date string"
    },
    {
      "name": "todayCompletionRate",
      "type": "Double",
      "description": "Number of today's completed habits divided by total active habits count (0.0 to 1.0)"
    },
    {
      "name": "todayCompletedCount",
      "type": "Int",
      "description": "Count of habits completed today for display in progress ring numerator"
    },
    {
      "name": "currentStreaks",
      "type": "[String: Int]",
      "description": "Maps each habit ID to its current consecutive-day streak count, computed by walking backwards from yesterday checking completion records"
    },
    {
      "name": "bestStreaks",
      "type": "[String: Int]",
      "description": "Maps each habit ID to its all-time longest streak, updated whenever currentStreak exceeds the stored best"
    },
    {
      "name": "weeklyCompletionRate",
      "type": "Double",
      "description": "Average of daily completion rates for the current Mon\u2013Sun week"
    },
    {
      "name": "previousWeekCompletionRate",
      "type": "Double",
      "description": "Same calculation for the prior week, used for trend comparison arrow"
    },
    {
      "name": "completionsByCategory",
      "type": "[HabitCategory: Double]",
      "description": "This week's completion rate per category, computed as average of per-habit rates within each category"
    },
    {
      "name": "dayOfWeekAverages",
      "type": "[Double]",
      "description": "Array of 7 doubles (Mon=0 through Sun=6) representing 4-week rolling average completion rate per weekday"
    },
    {
      "name": "heatmapData",
      "type": "[[Double]]",
      "description": "12-element array of 7-element arrays, each Double is a daily completion rate (0.0\u20131.0) for the calendar heatmap, ordered oldest week first"
    },
    {
      "name": "achievedMilestones",
      "type": "[(habitName: String, days: Int, date: Date)]",
      "description": "All milestone achievements (7, 30, 60, 100 day thresholds) across habits, sorted by date descending"
    },
    {
      "name": "atRiskStreaks",
      "type": "[HabitTrackerEntry]",
      "description": "Habits with active streaks of 3+ days that have NOT been completed today \u2014 shown as gentle reminders"
    }
  ],
  "domainLogic": {
    "dailyGoal": {
      "description": "Complete all active habits scheduled for today",
      "defaultValue": "100% of active habits"
    },
    "streakDefinition": "A streak counts consecutive days a habit was marked complete. Walking backwards from yesterday, each completed day increments the streak; the first missed day stops counting. If a habit targets fewer than 7 days/week, only scheduled days count \u2014 unscheduled days are transparent and do not break or extend the streak. Today's completion is shown visually but only locks into the streak at end-of-day. A streak resets to 0 on the first missed scheduled day.",
    "trendAnalysis": "Primary trend: this week's average daily completion rate vs last week's, shown as percentage delta with directional arrow. Secondary: per-category completion rates to identify neglected areas. Tertiary: day-of-week analysis using 4-week rolling average to surface strongest and weakest days.",
    "insights": [
      "Streak milestones: celebrate 7-day (bronze), 30-day (silver), 60-day (gold), 100-day (platinum) consecutive completions per habit",
      "At-risk streaks: surface habits with 3+ day streaks not yet completed today as gentle nudges",
      "Consistency score: percentage of all scheduled habit-days completed over the trailing 30 days",
      "Best day of week: which weekday has the highest 4-week rolling average completion rate",
      "Category balance: flag categories with completion rates below 50% as areas needing attention",
      "Trend direction: week-over-week completion rate change with positive/negative framing"
    ]
  }
}